[{"text":"Classes","collapsed":true,"items":[{"text":"TextmodeFigFont","link":"/api/textmode.figlet.js/classes/TextmodeFigFont.md"}]},{"text":"Interfaces","collapsed":true,"items":[{"text":"TextmodifierFigletExtensions","link":"/api/textmode.figlet.js/interfaces/TextmodifierFigletExtensions.md"},{"text":"FigFontHeader","link":"/api/textmode.figlet.js/interfaces/FigFontHeader.md"},{"text":"FigCharacter","link":"/api/textmode.figlet.js/interfaces/FigCharacter.md"},{"text":"FigTextCellContext","link":"/api/textmode.figlet.js/interfaces/FigTextCellContext.md"},{"text":"FigTextOptions","link":"/api/textmode.figlet.js/interfaces/FigTextOptions.md"}]},{"text":"Type Aliases","collapsed":true,"items":[{"text":"FigHorizontalLayout","link":"/api/textmode.figlet.js/type-aliases/FigHorizontalLayout.md"},{"text":"FigVerticalLayout","link":"/api/textmode.figlet.js/type-aliases/FigVerticalLayout.md"},{"text":"FigWrapMode","link":"/api/textmode.figlet.js/type-aliases/FigWrapMode.md"},{"text":"FigPrintDirection","link":"/api/textmode.figlet.js/type-aliases/FigPrintDirection.md"},{"text":"FigTextColorValue","link":"/api/textmode.figlet.js/type-aliases/FigTextColorValue.md"},{"text":"FigTextColorResolver","link":"/api/textmode.figlet.js/type-aliases/FigTextColorResolver.md"},{"text":"FigTextAlign","link":"/api/textmode.figlet.js/type-aliases/FigTextAlign.md"},{"text":"FigTextBaseline","link":"/api/textmode.figlet.js/type-aliases/FigTextBaseline.md"}]},{"text":"Variables","collapsed":true,"items":[{"text":"FigletPlugin","link":"/api/textmode.figlet.js/variables/FigletPlugin.md"}]}]